{
  "id": 10,
  "titre": "Wunnen",
  "titre_fr": "L'habitation – où j'habite",
  "couleur": "#5ad4a8",
  "instructions": {
    "flashcards": "Créer des cartes contenant des phrases complètes illustrant les différentes prépositions utilisées avec les lieux d'habitation. Les cartes doivent mettre en évidence les structures a/an, an der, zu, um/am et leurs traductions françaises.",
    "quiz": "Présenter une phrase française indiquant un lieu d'habitation. L'utilisateur doit choisir la bonne préposition luxembourgeoise. Les distracteurs doivent être les autres prépositions de la leçon (a, an, an der, zu, um, am).",
    "trous": "Créer des phrases de contexte avec des pays, villes, quartiers ou lieux. L'utilisateur doit retrouver la préposition correcte. Les distracteurs doivent être les autres prépositions étudiées dans la leçon.",
    "ecriture": "Faire produire des phrases complètes en luxembourgeois à partir du français. Réutiliser tous les cas importants de la leçon : pays sans article, pays féminins, Luxembourg, villes, quartiers et lieux."
  },
  "flashcards": [
    {
      "id": 1,
      "lu": "Ech wunnen a Frankräich.",
      "fr": "J'habite en France.",
      "note": "Pays sans article → a/an"
    },
    {
      "id": 2,
      "lu": "Ech wunnen an der Belsch.",
      "fr": "J'habite en Belgique.",
      "note": "Pays féminin → an der"
    },
    {
      "id": 3,
      "lu": "Ech wunnen zu Lëtzebuerg.",
      "fr": "J'habite au Luxembourg.",
      "note": "Exception → zu"
    },
    {
      "id": 4,
      "lu": "Ech wunnen zu Metz.",
      "fr": "J'habite à Metz.",
      "note": "Ville → zu"
    },
    {
      "id": 5,
      "lu": "Ech wunnen an der Stad.",
      "fr": "J'habite en ville.",
      "note": "Stad est féminin → an der"
    },
    {
      "id": 6,
      "lu": "Ech wunnen um Kirchberg.",
      "fr": "J'habite au Kirchberg.",
      "note": "Quartier → um/am"
    },
    {
      "id": 7,
      "lu": "Ech wunnen am Gronn.",
      "fr": "J'habite au Grund.",
      "note": "Quartier → um/am"
    },
    {
      "id": 8,
      "lu": "Wou wunns du?",
      "fr": "Où habites-tu ?",
      "note": "Question informelle → Ech wunnen zu Lëtzebuerg."
    },
    {
      "id": 9,
      "lu": "Wou wunnt Dir?",
      "fr": "Où habitez-vous ?",
      "note": "Question formelle → Ech wunnen an der Belsch."
    }
  ],
  "quiz": [
    {
      "id": 1,
      "question": "J'habite en France.",
      "reponse": "a Frankräich",
      "distracteurs": [
        "an der Frankräich",
        "zu Frankräich",
        "um Frankräich"
      ]
    },
    {
      "id": 2,
      "question": "J'habite en Belgique.",
      "reponse": "an der Belsch",
      "distracteurs": [
        "a Belsch",
        "zu Belsch",
        "um Belsch"
      ]
    },
    {
      "id": 3,
      "question": "J'habite au Luxembourg.",
      "reponse": "zu Lëtzebuerg",
      "distracteurs": [
        "a Lëtzebuerg",
        "an der Lëtzebuerg",
        "um Lëtzebuerg"
      ]
    },
    {
      "id": 4,
      "question": "J'habite à Metz.",
      "reponse": "zu Metz",
      "distracteurs": [
        "a Metz",
        "an der Metz",
        "um Metz"
      ]
    },
    {
      "id": 5,
      "question": "J'habite en ville.",
      "reponse": "an der Stad",
      "distracteurs": [
        "a Stad",
        "zu Stad",
        "um Stad"
      ]
    },
    {
      "id": 6,
      "question": "J'habite au Kirchberg.",
      "reponse": "um Kirchberg",
      "distracteurs": [
        "zu Kirchberg",
        "an der Kirchberg",
        "am Kirchberg"
      ]
    },
    {
      "id": 7,
      "question": "J'habite au Grund.",
      "reponse": "am Gronn",
      "distracteurs": [
        "um Gronn",
        "zu Gronn",
        "an der Gronn"
      ]
    },
    {
      "id": 8,
      "question": "J'habite en Espagne.",
      "reponse": "a Spuenien",
      "distracteurs": [
        "an der Spuenien",
        "zu Spuenien",
        "um Spuenien"
      ]
    },
    {
      "id": 9,
      "question": "J'habite à Paris.",
      "reponse": "zu Paräis",
      "distracteurs": [
        "a Paräis",
        "an der Paräis",
        "um Paräis"
      ]
    },
    {
      "id": 10,
      "question": "J'habite à Belair.",
      "reponse": "um Belair",
      "distracteurs": [
        "zu Belair",
        "an der Belair",
        "am Belair"
      ]
    },
    {
      "id": 11,
      "question": "J'habite en Suisse.",
      "reponse": "an der Schwäiz",
      "distracteurs": [
        "a Schwäiz",
        "zu Schwäiz",
        "um Schwäiz"
      ]
    }
  ],
  "trous": [
    {
      "id": 1,
      "fr": "J'habite au Luxembourg.",
      "avant": "Ech wunnen",
      "trou": "zu",
      "apres": "Lëtzebuerg.",
      "choix": [
        "a",
        "an",
        "zu",
        "an der",
        "um"
      ],
      "note": "Exception Luxembourg → zu"
    },
    {
      "id": 2,
      "fr": "J'habite en Allemagne.",
      "avant": "Ech wunnen",
      "trou": "an",
      "apres": "Däitschland.",
      "choix": [
        "a",
        "an",
        "zu",
        "an der",
        "um"
      ],
      "note": "Pays sans article"
    },
    {
      "id": 3,
      "fr": "J'habite en France.",
      "avant": "Ech wunnen",
      "trou": "a",
      "apres": "Frankräich.",
      "choix": [
        "a",
        "an",
        "zu",
        "an der",
        "um"
      ],
      "note": "Pays sans article"
    },
    {
      "id": 4,
      "fr": "J'habite en Belgique.",
      "avant": "Ech wunnen",
      "trou": "an der",
      "apres": "Belsch.",
      "choix": [
        "a",
        "an",
        "zu",
        "an der",
        "um"
      ],
      "note": "Pays féminin"
    },
    {
      "id": 5,
      "fr": "J'habite en Suisse.",
      "avant": "Ech wunnen",
      "trou": "an der",
      "apres": "Schwäiz.",
      "choix": [
        "a",
        "an",
        "zu",
        "an der",
        "um"
      ],
      "note": "Pays féminin"
    },
    {
      "id": 6,
      "fr": "J'habite à Metz.",
      "avant": "Ech wunnen",
      "trou": "zu",
      "apres": "Metz.",
      "choix": [
        "a",
        "an",
        "zu",
        "an der",
        "um"
      ],
      "note": "Ville"
    },
    {
      "id": 7,
      "fr": "J'habite à Esch.",
      "avant": "Ech wunnen",
      "trou": "zu",
      "apres": "Esch.",
      "choix": [
        "a",
        "an",
        "zu",
        "an der",
        "um"
      ],
      "note": "Ville"
    },
    {
      "id": 8,
      "fr": "J'habite à Trèves.",
      "avant": "Ech wunnen",
      "trou": "zu",
      "apres": "Tréier.",
      "choix": [
        "a",
        "an",
        "zu",
        "an der",
        "um"
      ],
      "note": "Ville"
    },
    {
      "id": 9,
      "fr": "J'habite en ville.",
      "avant": "Ech wunnen",
      "trou": "an der",
      "apres": "Stad.",
      "choix": [
        "a",
        "an",
        "zu",
        "an der",
        "um"
      ],
      "note": "Stad est féminin"
    },
    {
      "id": 10,
      "fr": "J'habite au Kirchberg.",
      "avant": "Ech wunnen",
      "trou": "um",
      "apres": "Kirchberg.",
      "choix": [
        "a",
        "an",
        "zu",
        "an der",
        "um"
      ],
      "note": "Quartier"
    },
    {
      "id": 11,
      "fr": "J'habite à Belair.",
      "avant": "Ech wunnen",
      "trou": "um",
      "apres": "Belair.",
      "choix": [
        "a",
        "an",
        "zu",
        "an der",
        "um"
      ],
      "note": "Quartier"
    },
    {
      "id": 12,
      "fr": "J'habite au Limpertsberg.",
      "avant": "Ech wunnen",
      "trou": "um",
      "apres": "Limpertsberg.",
      "choix": [
        "a",
        "an",
        "zu",
        "an der",
        "um"
      ],
      "note": "Quartier"
    },
    {
      "id": 13,
      "fr": "J'habite au Grund.",
      "avant": "Ech wunnen",
      "trou": "am",
      "apres": "Gronn.",
      "choix": [
        "a",
        "an",
        "zu",
        "an der",
        "am"
      ],
      "note": "Quartier → am"
    },
    {
      "id": 14,
      "fr": "J'habite en Belgique.",
      "avant": "Ech wunnen",
      "trou": "an der",
      "apres": "Belsch.",
      "choix": [
        "a",
        "zu",
        "um",
        "an der"
      ],
      "note": "Révision pays féminin"
    },
    {
      "id": 15,
      "fr": "J'habite à Luxembourg-ville.",
      "avant": "Ech wunnen",
      "trou": "zu",
      "apres": "Lëtzebuerg-Stad.",
      "choix": [
        "a",
        "an",
        "zu",
        "an der"
      ],
      "note": "Ville"
    },
    {
      "id": 16,
      "fr": "J'habite en France.",
      "avant": "Ech wunnen",
      "trou": "a",
      "apres": "Frankräich.",
      "choix": [
        "a",
        "an",
        "zu",
        "an der"
      ],
      "note": "Révision pays sans article"
    }
  ],
  "ecriture": [
    {
      "fr": "J'habite au Luxembourg.",
      "lu": "Ech wunnen zu Lëtzebuerg."
    },
    {
      "fr": "J'habite en Allemagne.",
      "lu": "Ech wunnen an Däitschland."
    },
    {
      "fr": "J'habite en France.",
      "lu": "Ech wunnen a Frankräich."
    },
    {
      "fr": "J'habite en Belgique.",
      "lu": "Ech wunnen an der Belsch."
    },
    {
      "fr": "J'habite en Suisse.",
      "lu": "Ech wunnen an der Schwäiz."
    },
    {
      "fr": "J'habite en Espagne.",
      "lu": "Ech wunnen a Spuenien."
    },
    {
      "fr": "J'habite en Italie.",
      "lu": "Ech wunnen an Italien."
    },
    {
      "fr": "J'habite en Angleterre.",
      "lu": "Ech wunnen an England."
    },
    {
      "fr": "J'habite aux Pays-Bas.",
      "lu": "Ech wunnen a Holland."
    },
    {
      "fr": "J'habite en Suède.",
      "lu": "Ech wunnen a Schweden."
    },
    {
      "fr": "J'habite en Chine.",
      "lu": "Ech wunnen a China."
    },
    {
      "fr": "J'habite à Metz.",
      "lu": "Ech wunnen zu Metz."
    },
    {
      "fr": "J'habite à Esch.",
      "lu": "Ech wunnen zu Esch."
    },
    {
      "fr": "J'habite à Trèves.",
      "lu": "Ech wunnen zu Tréier."
    },
    {
      "fr": "Elle habite à Paris.",
      "lu": "Si wunnt zu Paräis."
    },
    {
      "fr": "J'habite à Paris.",
      "lu": "Ech wunnen zu Paräis."
    },
    {
      "fr": "J'habite à Luxembourg-Ville.",
      "lu": "Ech wunnen zu Lëtzebuerg-Stad."
    },
    {
      "fr": "J'habite en ville.",
      "lu": "Ech wunnen an der Stad."
    },
    {
      "fr": "J'habite au Kirchberg.",
      "lu": "Ech wunnen um Kirchberg."
    },
    {
      "fr": "J'habite à Belair.",
      "lu": "Ech wunnen um Belair."
    },
    {
      "fr": "J'habite au Limpertsberg.",
      "lu": "Ech wunnen um Limpertsberg."
    },
    {
      "fr": "J'habite au Grund.",
      "lu": "Ech wunnen am Gronn."
    },
    {
      "fr": "Où habites-tu ?",
      "lu": "Wou wunns du?"
    },
    {
      "fr": "Où habitez-vous ?",
      "lu": "Wou wunnt Dir?"
    },
    {
      "fr": "Il habite au Luxembourg.",
      "lu": "Hien wunnt zu Lëtzebuerg."
    },
    {
      "fr": "Elle habite en Belgique.",
      "lu": "Si wunnt an der Belsch."
    },
    {
      "fr": "Nous habitons à Luxembourg-Ville.",
      "lu": "Mir wunnen zu Lëtzebuerg-Stad."
    },
    {
      "fr": "Il habite à Belair.",
      "lu": "Hien wunnt um Belair."
    },
    {
      "fr": "Elle habite au Grund.",
      "lu": "Si wunnt am Gronn."
    },
    {
      "fr": "habiter",
      "lu": "wunnen"
    },
    {
      "fr": "la ville",
      "lu": "d'Stad"
    },
    {
      "fr": "le quartier",
      "lu": "de Quartier"
    },
    {
      "fr": "Grund",
      "lu": "Gronn"
    }
  ],
  "cours": [
    {
      "type": "texte",
      "contenu": "Pour dire où on habite, on utilise le verbe <b>wunnen</b> avec une préposition qui dépend du type de lieu : pays, ville, quartier ou lieu."
    },
    {
      "type": "regle",
      "titre": "Les prépositions pour parler de son lieu d'habitation",
      "lignes": [
        "Luxembourg → <b>zu Lëtzebuerg</b>",
        "Ville → <b>zu</b> (zu Metz, zu Esch, zu Paräis)",
        "Pays sans article → <b>a / an</b> (a Frankräich, an Däitschland)",
        "Pays féminins → <b>an der</b> (an der Belsch, an der Schwäiz)",
        "Ville (au sens général) → <b>an der Stad</b>",
        "Quartiers et lieux → <b>um / am</b> (um Kirchberg, um Belair, am Gronn)"
      ]
    },
    {
      "type": "vocab",
      "titre": "Vocabulaire",
      "items": [
        [
          "wunnen",
          "habiter"
        ],
        [
          "d'Stad",
          "la ville"
        ],
        [
          "de Quartier",
          "le quartier"
        ],
        [
          "Lëtzebuerg",
          "Luxembourg"
        ],
        [
          "Belsch",
          "Belgique"
        ],
        [
          "Schwäiz",
          "Suisse"
        ],
        [
          "Däitschland",
          "Allemagne"
        ],
        [
          "Frankräich",
          "France"
        ],
        [
          "Metz",
          "Metz"
        ],
        [
          "Esch",
          "Esch"
        ],
        [
          "Tréier",
          "Trèves"
        ],
        [
          "Kirchberg",
          "Kirchberg"
        ],
        [
          "Belair",
          "Belair"
        ],
        [
          "Gronn",
          "Grund"
        ]
      ]
    },
    {
      "type": "dialogue",
      "titre": "Exemples",
      "echanges": [
        [
          "Ech wunnen zu Lëtzebuerg.",
          "J'habite au Luxembourg."
        ],
        [
          "Ech wunnen a Frankräich.",
          "J'habite en France."
        ],
        [
          "Ech wunnen an der Belsch.",
          "J'habite en Belgique."
        ],
        [
          "Ech wunnen zu Metz.",
          "J'habite à Metz."
        ],
        [
          "Ech wunnen um Kirchberg.",
          "J'habite au Kirchberg."
        ],
        [
          "Ech wunnen am Gronn.",
          "J'habite au Grund."
        ]
      ]
    },
    {
      "type": "dialogue",
      "titre": "Demander où quelqu'un habite",
      "echanges": [
        [
          "Wou wunns du?",
          "Où habites-tu ?"
        ],
        [
          "Wou wunnt Dir?",
          "Où habitez-vous ?"
        ]
      ]
    }
  ]
}